almasql/__init__.py
almasql/_directives_.py
almasql/_post_join_.py
almasql/_query_.py
almasql/_testing/_my_/__init__.py
almasql/_testing/_my_/_almasql_assert_.py
almasql/_testing/_my_/_settings_.py
almasql/_testing/test_queries.py
almasql/_transaction_.py
almasql/_transactions_chain_.py
almasql-0.2.6.dist-info/LICENSE.txt
almasql-0.2.6.dist-info/METADATA
almasql-0.2.6.dist-info/WHEEL
almasql-0.2.6.dist-info/RECORD
