Metadata-Version: 2.1
Name: almasql
Version: 0.2.6
Summary: Simple library for dynamic SQL queries
Home-page: https://github.com/aturkenov/almasql
License: MIT
Keywords: SQL,AlmaSQL
Author: aturkenov
Requires-Python: >=3.12,<4.0
Classifier: License :: OSI Approved :: MIT License
Classifier: Programming Language :: Python :: 3
Classifier: Programming Language :: Python :: 3.12
Classifier: Topic :: Software Development :: Build Tools
Classifier: Topic :: Software Development :: Libraries :: Python Modules
Requires-Dist: greenlet (>=3.0.3,<4.0.0)
Requires-Dist: jinja2 (>=3.1.4,<4.0.0)
Requires-Dist: sqlalchemy (>=2.0.30,<3.0.0)
Project-URL: Documentation, https://github.com/aturkenov/almasql
Project-URL: Repository, https://github.com/aturkenov/almasql
